dfs/__init__.py
dfs/dfs.py
dfs/graph.py
graph_dfs-0.0.8.dist-info/LICENSE.txt
graph_dfs-0.0.8.dist-info/WHEEL
graph_dfs-0.0.8.dist-info/METADATA
graph_dfs-0.0.8.dist-info/RECORD
