Metadata-Version: 2.1
Name: graph-dfs
Version: 0.0.8
Summary: Graphs and Depth First Search
Home-page: https://github.com/daniel-ufabc/graph-dfs
License: MIT
Keywords: graph,DFS
Author: Daniel M. Martin
Author-email: danielmmartin@gmail.com
Requires-Python: >=3.7,<4.0
Classifier: License :: OSI Approved :: MIT License
Classifier: Programming Language :: Python :: 3
Classifier: Programming Language :: Python :: 3.7
Classifier: Programming Language :: Python :: 3.8
Classifier: Programming Language :: Python :: 3.9
Classifier: Topic :: Software Development :: Libraries
Project-URL: Repository, https://github.com/daniel-ufabc/graph-dfs
